MrdStudioLogger/__init__.py
MrdStudioLogger/middleware.py
mrdstudiologger-0.1.7.dist-info/METADATA
mrdstudiologger-0.1.7.dist-info/WHEEL
mrdstudiologger-0.1.7.dist-info/top_level.txt
mrdstudiologger-0.1.7.dist-info/RECORD
