Metadata-Version: 2.4
Name: MrdStudioLogger
Version: 0.1.7
Summary: Rich-powered dual-column logging middleware for FastAPI
Author-email: szdunek <zdunek.sylwiusz@gmail.com>
License: MIT
Project-URL: Homepage, https://mrd-studio.pl
Requires-Python: >=3.8
Requires-Dist: fastapi
Requires-Dist: rich
